resuMe/__init__.py
resuMe/main.py
resuMe/scraping.py
resuMe/utils.py
resuMe/commands/__init__.py
resuMe/commands/build.py
resuMe/commands/delete.py
resuMe/commands/deploy.py
resuMe/commands/init.py
resuMe/commands/list.py
resuMe/commands/update.py
resume_cli-0.1.5.dist-info/LICENSE
resume_cli-0.1.5.dist-info/METADATA
resume_cli-0.1.5.dist-info/WHEEL
resume_cli-0.1.5.dist-info/entry_points.txt
resume_cli-0.1.5.dist-info/top_level.txt
resume_cli-0.1.5.dist-info/RECORD
