Metadata-Version: 2.1
Name: resume-cli
Version: 0.1.5
Summary: UNKNOWN
Home-page: UNKNOWN
License: UNKNOWN
Platform: UNKNOWN
License-File: LICENSE
Requires-Dist: click (==7.1.2)
Requires-Dist: PyInquirer (==1.0.3)
Requires-Dist: selenium (==3.141.0)
Requires-Dist: bs4 (==0.0.1)
Requires-Dist: requests (==2.26.0)
Requires-Dist: lxml (==4.6.3)
Requires-Dist: webdriver-manager (==3.4.1)
Requires-Dist: colorama (==0.4.4)
Requires-Dist: psutil (==5.8.0)
